rfflearn/rfflearn_common.py
rfflearn/cpu/__init__.py
rfflearn/cpu/rfflearn_cpu_cca.py
rfflearn/cpu/rfflearn_cpu_common.py
rfflearn/cpu/rfflearn_cpu_gp.py
rfflearn/cpu/rfflearn_cpu_pca.py
rfflearn/cpu/rfflearn_cpu_regression.py
rfflearn/cpu/rfflearn_cpu_svc.py
rfflearn/cpu/rfflearn_cpu_svr.py
rfflearn/explainer/__init__.py
rfflearn/explainer/permutation.py
rfflearn/explainer/shapley.py
rfflearn/gpu/__init__.py
rfflearn/gpu/rfflearn_gpu_common.py
rfflearn/gpu/rfflearn_gpu_gp.py
rfflearn/gpu/rfflearn_gpu_pca.py
rfflearn/gpu/rfflearn_gpu_svc.py
rfflearn/tuner/__init__.py
rfflearn/tuner/hptuner.py
rfflearn-2024.10.28.dist-info/METADATA
rfflearn-2024.10.28.dist-info/WHEEL
rfflearn-2024.10.28.dist-info/licenses/LICENSE
rfflearn-2024.10.28.dist-info/RECORD
