Metadata-Version: 2.3
Name: rfflearn
Version: 2024.10.28
Summary: Implementation of random Fourier features for kernel method, like support vector machine and Gaussian process model
Project-URL: Repository, https://github.com/tiskw/random-fourier-features
Project-URL: Issues, https://github.com/tiskw/random-fourier-features/issues
Author-email: Tetsuya Ishikawa <tiskw111@gmail.com>
License: MIT License
License-File: LICENSE
Classifier: Development Status :: 4 - Beta
Classifier: Intended Audience :: Developers
Classifier: License :: OSI Approved :: MIT License
Classifier: Operating System :: OS Independent
Classifier: Programming Language :: Python :: 3
Requires-Python: >=3.9
Requires-Dist: numpy>=1.19.0
Requires-Dist: pandas>=1.2.1
Requires-Dist: scikit-learn>=0.24.0
Requires-Dist: scipy>=1.6.0
